README.rst
setup.py
pdbreak/__init__.py
pdbreak.egg-info/PKG-INFO
pdbreak.egg-info/SOURCES.txt
pdbreak.egg-info/dependency_links.txt
pdbreak.egg-info/top_level.txt